[
	{
		"__TYPE__": "SharedSliceContent",
		"variation": "default",
		"primary": {
			"button_link": {
				"__TYPE__": "LinkContent",
				"value": {
					"__TYPE__": "ExternalLink",
					"url": "https://github.com",
					"target": "_blank"
				}
			},
			"button_text": {
				"__TYPE__": "FieldContent",
				"type": "Text",
				"value": "VIEW WORK"
			},
			"project_title": {
				"__TYPE__": "StructuredTextContent",
				"value": [
					{
						"type": "paragraph",
						"content": {
							"text": "REAL ESTATE TEMPLATE",
							"spans": []
						},
						"direction": "ltr"
					}
				]
			},
			"description": {
				"__TYPE__": "FieldContent",
				"type": "Text",
				"value": "Lorem ipsum dolor sit amet, consectetur"
			},
			"description_bold": {
				"__TYPE__": "FieldContent",
				"type": "Text",
				"value": "adipiscing elit. Ultrices lorem non feugiat egestas amet."
			},
			"category": {
				"__TYPE__": "StructuredTextContent",
				"value": [
					{
						"type": "paragraph",
						"content": {
							"text": "Website Design",
							"spans": []
						},
						"direction": "ltr"
					}
				]
			},
			"image": {
				"origin": {
					"id": "main",
					"url": "https://images.unsplash.com/photo-1496181133206-80ce9b88a853",
					"width": 5243,
					"height": 3495
				},
				"url": "https://images.unsplash.com/photo-1496181133206-80ce9b88a853",
				"width": 5243,
				"height": 3495,
				"edit": {
					"zoom": 1,
					"crop": {
						"x": 0,
						"y": 0
					},
					"background": "transparent"
				},
				"credits": null,
				"alt": null,
				"__TYPE__": "ImageContent",
				"thumbnails": {}
			}
		},
		"items": []
	}
]